datasette_query_links/__init__.py
datasette_query_links-0.1.2.dist-info/METADATA
datasette_query_links-0.1.2.dist-info/WHEEL
datasette_query_links-0.1.2.dist-info/entry_points.txt
datasette_query_links-0.1.2.dist-info/top_level.txt
datasette_query_links-0.1.2.dist-info/RECORD
