Metadata-Version: 2.1
Name: datasette-query-links
Version: 0.1.2
Summary: Turn SELECT queries returned by a query into links to execute them
Home-page: https://github.com/simonw/datasette-query-links
Author: Simon Willison
License: Apache License, Version 2.0
Project-URL: Issues, https://github.com/simonw/datasette-query-links/issues
Project-URL: CI, https://github.com/simonw/datasette-query-links/actions
Project-URL: Changelog, https://github.com/simonw/datasette-query-links/releases
Platform: UNKNOWN
Requires-Python: >=3.6
Requires-Dist: datasette (>=0.59a1)
Provides-Extra: test
Requires-Dist: pytest ; extra == 'test'
Requires-Dist: pytest-asyncio ; extra == 'test'
Requires-Dist: beautifulsoup4 ; extra == 'test'
